draupnir/3D.py
draupnir/__init__.py
draupnir/datasets.py
draupnir/draw_tree.py
draupnir/guides.py
draupnir/load_utils.py
draupnir/main.py
draupnir/models.py
draupnir/models_utils.py
draupnir/mutual_information.py
draupnir/plots.py
draupnir/train.py
draupnir/utils.py
draupnir/data/AA_properties.txt
draupnir/data/PfamPdbMap.txt
draupnir/infer_angles/__init__.py
draupnir/infer_angles/calculate_coords.py
draupnir/infer_angles/nerf.py
draupnir/infer_angles/pnerf.py
draupnir/infer_angles/superposition.py
draupnir-0.0.193.dist-info/LICENSE
draupnir-0.0.193.dist-info/METADATA
draupnir-0.0.193.dist-info/WHEEL
draupnir-0.0.193.dist-info/top_level.txt
draupnir-0.0.193.dist-info/RECORD
